{
  "subject": "FIN",
  "scrapedAt": 1768543685329,
  "courseCount": 66,
  "courses": {
    "FIN 390": [
      "Finance Academy",
      {
        "FA": [
          "55580",
          [
            [
              25,
              "TR",
              "1100 Wymer Hall",
              7,
              [
                "Excell, R"
              ],
              -1,
              -1,
              -1
            ]
          ],
          3,
          0,
          0,
          [],
          -1
        ],
        "FA2": [
          "77775",
          [
            [
              0,
              "MW",
              "1001 Business Instructional Fac",
              16,
              [
                "Burwitz, J"
              ],
              -1,
              -1,
              -1
            ]
          ],
          3,
          0,
          0,
          [],
          -1
        ]
      },
      [],
      "A program aimed at preparing students for Golder Academies open to all second-semester students at Gies. Its goals are to equip students with essential technical skills for career advancement and to enhance their job recruitment understanding. Skills developed will also support academic success in upper-level Finance courses.",
      []
    ],
    "FIN 221": [
      "Corporate Finance",
      {
        "AL2": [
          "32519",
          [
            [
              3,
              "MW",
              "1001 Business Instructional Fac",
              16,
              [
                "Satchell, J"
              ],
              -1,
              -1,
              -1
            ]
          ],
          3,
          2,
          0,
          [],
          -1
        ],
        "AL3": [
          "51083",
          [
            [
              4,
              "MW",
              "1001 Business Instructional Fac",
              16,
              [
                "Satchell, J"
              ],
              -1,
              -1,
              -1
            ]
          ],
          3,
          2,
          0,
          [],
          -1
        ],
        "D01": [
          "32524",
          [
            [
              3,
              "F",
              "2020 Wymer Hall",
              7,
              [
                "Rafat Nezhad, R"
              ],
              -1,
              -1,
              -1
            ]
          ],
          3,
          1,
          0,
          [],
          -1
        ],
        "D02": [
          "32562",
          [
            [
              3,
              "F",
              "2060 Wymer Hall",
              7,
              [
                "Tsai, A"
              ],
              -1,
              -1,
              -1
            ]
          ],
          3,
          1,
          0,
          [],
          -1
        ],
        "D03": [
          "32522",
          [
            [
              4,
              "F",
              "2060 Wymer Hall",
              7,
              [
                "Tsai, A"
              ],
              -1,
              -1,
              -1
            ]
          ],
          3,
          1,
          0,
          [],
          -1
        ],
        "D04": [
          "32523",
          [
            [
              4,
              "F",
              "2020 Wymer Hall",
              7,
              [
                "Rafat Nezhad, R"
              ],
              -1,
              -1,
              -1
            ]
          ],
          3,
          1,
          0,
          [],
          -1
        ],
        "D05": [
          "32563",
          [
            [
              7,
              "F",
              "2060 Wymer Hall",
              7,
              [
                "Rafat Nezhad, R"
              ],
              -1,
              -1,
              -1
            ]
          ],
          3,
          1,
          0,
          [],
          -1
        ],
        "D06": [
          "32529",
          [
            [
              7,
              "F",
              "2020 Wymer Hall",
              7,
              [
                "Tsai, A"
              ],
              -1,
              -1,
              -1
            ]
          ],
          3,
          1,
          0,
          [],
          -1
        ],
        "D07": [
          "32530",
          [
            [
              8,
              "F",
              "2020 Wymer Hall",
              7,
              [
                "Tsai, A"
              ],
              -1,
              -1,
              -1
            ]
          ],
          3,
          1,
          0,
          [],
          -1
        ],
        "D08": [
          "32531",
          [
            [
              8,
              "F",
              "2060 Wymer Hall",
              7,
              [
                "Rafat Nezhad, R"
              ],
              -1,
              -1,
              -1
            ]
          ],
          3,
          1,
          0,
          [],
          -1
        ],
        "D09": [
          "32540",
          [
            [
              23,
              "F",
              "2060 Wymer Hall",
              7,
              [
                "Rafat Nezhad, R"
              ],
              -1,
              -1,
              -1
            ]
          ],
          3,
          1,
          0,
          [],
          -1
        ],
        "D10": [
          "32556",
          [
            [
              23,
              "F",
              "2020 Wymer Hall",
              7,
              [
                "Tsai, A"
              ],
              -1,
              -1,
              -1
            ]
          ],
          3,
          1,
          0,
          [],
          -1
        ],
        "ONL": [
          "60404",
          [
            [
              12,
              "",
              "ONLINE",
              7,
              [
                "Raskie, S"
              ],
              -1,
              -1,
              -1
            ]
          ],
          3,
          3,
          0,
          [],
          -1
        ],
        "RL1": [
          "32518",
          [
            [
              27,
              "MW",
              "1001 Business Instructional Fac",
              16,
              [
                "Satchell, J"
              ],
              -1,
              -1,
              -1
            ]
          ],
          3,
          2,
          0,
          [],
          -1
        ]
      },
      [],
      "Introductory study of corporate financial management, in particular how the financial manager's choices add value to shareholder wealth through investment financing and operating decisions.",
      []
    ],
    "FIN 230": [
      "Introduction to Insurance",
      {
        "ONL": [
          "69274",
          [
            [
              12,
              "",
              "ONLINE",
              7,
              [
                "Thomas, T"
              ],
              -1,
              -1,
              -1
            ]
          ],
          3,
          3,
          0,
          [],
          -1
        ],
        "P": [
          "46691",
          [
            [
              0,
              "MW",
              "1100 Wymer Hall",
              7,
              [
                "Beigie, D"
              ],
              -1,
              -1,
              -1
            ]
          ],
          3,
          0,
          0,
          [],
          -1
        ]
      },
      [],
      "Introductory course on the role of insurance in society; covers insurance terminology, common personal insurance policies (auto, health, life and homeowners) and current issues.",
      []
    ],
    "FIN 380": [
      "Entrepreneurship through Acquisition",
      {
        "ETA": [
          "74427",
          [
            [
              114,
              "MW",
              "2043 Business Instructional Fac",
              16,
              [
                "Smith, M"
              ],
              -1,
              -1,
              -1
            ]
          ],
          2,
          0,
          0,
          [],
          -1
        ]
      },
      [],
      "Focuses on the process involved in Entrepreneurship through Acquisition, i.e., acquiring and growing an existing small business. The course will be combination of lectures and presentations by invited speakers, including research professionals, bankers, accountants, and attorneys specializing in small company deals, business brokers, PE and VC professionals, and entrepreneurs who have bought a small business or are in the process of buying a small business.",
      []
    ],
    "FIN 392": [
      "Investment Management Academy",
      {
        "IMA": [
          "65039",
          [
            [
              0,
              "TR",
              "100 Gregory Hall",
              1,
              [
                "Excell, R",
                "Vitek, M"
              ],
              -1,
              -1,
              -1
            ]
          ],
          1,
          0,
          0,
          [],
          -1
        ]
      },
      [],
      "Overview of security analysis with the objective of how to value an investment proposition for inclusion in a portfolio of securities managed by students in the class. Focus will be in areas of fundamental securities analysis with the emphasis on equity valuation. Course will not satisfy Finance major requirements.",
      []
    ],
    "FIN 321": [
      "Advanced Corporate Finance",
      {
        "C1": [
          "44635",
          [
            [
              13,
              "MW",
              "2010 Wymer Hall",
              7,
              [
                "Huang, C"
              ],
              -1,
              -1,
              -1
            ]
          ],
          3,
          0,
          0,
          [],
          -1
        ],
        "D": [
          "40593",
          [
            [
              26,
              "MW",
              "2010 Wymer Hall",
              7,
              [
                "Huang, C"
              ],
              -1,
              -1,
              -1
            ]
          ],
          3,
          0,
          0,
          [],
          -1
        ],
        "F": [
          "32613",
          [
            [
              0,
              "MW",
              "240 Wohlers Hall",
              9,
              [
                "Xu, Q"
              ],
              -1,
              -1,
              -1
            ]
          ],
          3,
          0,
          0,
          [],
          -1
        ],
        "S": [
          "32614",
          [
            [
              11,
              "MW",
              "2007 Business Instructional Fac",
              16,
              [
                "Huang, C"
              ],
              -1,
              -1,
              -1
            ]
          ],
          3,
          0,
          0,
          [],
          -1
        ]
      },
      [],
      "Theories of firms' investment and financing decisions are covered. Topics include dividend policy, capital budgeting, capital structure, bankruptcy, long- term debt and leasing decisions.",
      []
    ],
    "FIN 391": [
      "Investment Banking Academy",
      {
        "IBA": [
          "62414",
          [
            [
              11,
              "TR",
              "241 Wohlers Hall",
              9,
              [
                "Bertram, J"
              ],
              -1,
              -1,
              -1
            ]
          ],
          1,
          0,
          0,
          [],
          -1
        ]
      },
      [],
      "A diversified curriculum designed to prepare students for a successful career in investment banking; course incorporates peer mentorship, guest lectures (from bankers, accountants, private equity associates and hedge fund analysts), a case competition and a field trip. Course will not satisfy Finance major requirements.",
      []
    ],
    "FIN 300": [
      "Financial Markets",
      {
        "C": [
          "32594",
          [
            [
              2,
              "TR",
              "243 Wohlers Hall",
              9,
              [
                "Peters, S"
              ],
              -1,
              -1,
              -1
            ]
          ],
          3,
          0,
          0,
          [],
          -1
        ],
        "D": [
          "32593",
          [
            [
              0,
              "TR",
              "243 Wohlers Hall",
              9,
              [
                "Peters, S"
              ],
              -1,
              -1,
              -1
            ]
          ],
          3,
          0,
          0,
          [],
          -1
        ],
        "P1": [
          "39481",
          [
            [
              0,
              "TR",
              "3001 Business Instructional Fac",
              16,
              [
                "Marcinkowski, M"
              ],
              -1,
              -1,
              -1
            ]
          ],
          3,
          0,
          0,
          [],
          -1
        ],
        "S": [
          "49208",
          [
            [
              11,
              "TR",
              "3003 Business Instructional Fac",
              16,
              [
                "Marcinkowski, M"
              ],
              -1,
              -1,
              -1
            ]
          ],
          3,
          0,
          0,
          [],
          -1
        ],
        "S2": [
          "32601",
          [
            [
              11,
              "TR",
              "240 Wohlers Hall",
              9,
              [
                "Peters, S"
              ],
              -1,
              -1,
              -1
            ]
          ],
          3,
          0,
          0,
          [],
          -1
        ],
        "S3": [
          "40578",
          [
            [
              26,
              "MW",
              "2057 Business Instructional Fac",
              16,
              [
                "Smith, M"
              ],
              -1,
              -1,
              -1
            ]
          ],
          3,
          0,
          0,
          [],
          -1
        ]
      },
      [],
      "Theory and applications associated with the functioning of financial markets to include the conceptual foundations of portfolio theory, risk management, and asset valuation. The stock, money, bond, mortgage, and futures and options markets are examined.",
      []
    ],
    "FIN 241": [
      "Fundamentals of Real Estate",
      {
        "D": [
          "43820",
          [
            [
              2,
              "MW",
              "2001 Business Instructional Fac",
              16,
              [
                "Sehy, A"
              ],
              -1,
              -1,
              -1
            ]
          ],
          3,
          0,
          0,
          [],
          -1
        ],
        "ONL": [
          "43818",
          [
            [
              12,
              "",
              "ONLINE",
              7,
              [
                "Perkins, S"
              ],
              -1,
              -1,
              -1
            ]
          ],
          3,
          3,
          0,
          [],
          -1
        ]
      },
      [],
      "A survey of real estate finance, appraisal, investment, law, brokerage, management, development and economics. Special attention is given to the analysis of aggregate real estate and mortgage markets, to the individual transactions within these markets, and to the legal and institutional factors which affect these markets.",
      []
    ],
    "FIN 199": [
      "Undergraduate Open Seminar",
      {
        "": [
          "10109",
          [
            [
              12,
              "",
              "ONLINE",
              7,
              [
                "Staff"
              ],
              -1,
              -1,
              -1
            ]
          ],
          5,
          4,
          0,
          [],
          -1
        ]
      },
      [],
      "Approved for letter and S/U grading. Course may be repeated for credit.",
      []
    ],
    "FIN 393": [
      "Risk Management Academy",
      {
        "RMA": [
          "71623",
          [
            [
              38,
              "W",
              "2041 Business Instructional Fac",
              16,
              [
                "Beigie, D"
              ],
              -1,
              -1,
              -1
            ]
          ],
          1,
          0,
          0,
          [],
          -1
        ]
      },
      [],
      "The Risk Management Academy is an enrichment program for outstanding undergraduates from across campus. The nature of risk management requires a knowledge base that includes majors from a number of colleges and departments including Finance, Actuarial Science, Atmospheric Sciences, Financial Planning, Engineering, Math and Statistics. RMA provides a select program that focuses on developing future business leaders in risk management via enhanced academic and career opportunities. Students are normally invited to participate by the faculty during their freshman or sophomore year, when they are enrolled in FIN 230 and other basic RM courses. If inducted/accepted, students participate throughout their sophomore, junior and senior years.",
      []
    ],
    "FIN 411": [
      "Investment & Portfolio Mngt",
      {
        "D": [
          "55576",
          [
            [
              11,
              "TR",
              "3007 Business Instructional Fac",
              16,
              [
                "Spencer, X"
              ],
              -1,
              -1,
              -1
            ]
          ],
          3,
          0,
          0,
          [],
          -1
        ],
        "E": [
          "55575",
          [
            [
              11,
              "TR",
              "2043 Business Instructional Fac",
              16,
              [
                "Chen, Y"
              ],
              -1,
              -1,
              -1
            ]
          ],
          3,
          0,
          0,
          [],
          -1
        ],
        "PM2": [
          "55577",
          [
            [
              2,
              "TR",
              "3001 Business Instructional Fac",
              16,
              [
                "Chen, Y"
              ],
              -1,
              -1,
              -1
            ]
          ],
          3,
          0,
          0,
          [],
          -1
        ],
        "S": [
          "55578",
          [
            [
              26,
              "TR",
              "2063 Business Instructional Fac",
              16,
              [
                "Chen, Y"
              ],
              -1,
              -1,
              -1
            ]
          ],
          3,
          0,
          0,
          [],
          -1
        ]
      },
      [],
      "Current theories of portfolio management are covered in considerable detail to provide a conceptual framework for the evaluation of investment strategies. Applications and implementation are covered in depth, including performance evaluation and international diversification.",
      []
    ],
    "FIN 412": [
      "Options and Futures Markets",
      {
        "K1": [
          "32650",
          [
            [
              0,
              "TR",
              "2057 Business Instructional Fac",
              16,
              [
                "Kargar, M"
              ],
              -1,
              -1,
              -1
            ]
          ],
          3,
          0,
          0,
          [],
          -1
        ]
      },
      [],
      "Introduction of options and futures markets for financial assets; examination of institutional aspects of the markets; theories of pricing; discussion of simple as well as complicated trading strategies (arbitrage, hedging and spread); applications for asset and risk management.",
      []
    ],
    "FIN 418": [
      "Financial Modeling",
      {
        "FM1": [
          "53199",
          [
            [
              2,
              "MW",
              "1049 Business Instructional Fac",
              16,
              [
                "Kennemore, D"
              ],
              -1,
              -1,
              -1
            ]
          ],
          3,
          0,
          0,
          [],
          -1
        ],
        "FM3": [
          "75505",
          [
            [
              11,
              "MW",
              "3039 Business Instructional Fac",
              16,
              [
                "Kennemore, D"
              ],
              -1,
              -1,
              -1
            ]
          ],
          3,
          0,
          0,
          [],
          -1
        ],
        "RE": [
          "53200",
          [
            [
              13,
              "MW",
              "2041 Business Instructional Fac",
              16,
              [
                "Grimsley, K"
              ],
              -1,
              -1,
              -1
            ]
          ],
          3,
          0,
          0,
          [],
          -1
        ]
      },
      [],
      "The objective is to learn the fundamentals and practice building financial models using Microsoft Excel. By the end of the term, each student should be able to develop an understanding of any financial relationship and build that financial relationship into a model using the built-in functions of Excel. Financial modeling, by definition, requires significant work outside of the classroom. Models are introduced, demonstrated, and reviewed in class, but each student is expected to research and collect date, and to construct the models, prior to each week's class meeting.",
      []
    ],
    "FIN 395": [
      "Real Estate Finance Academy",
      {
        "B1": [
          "76374",
          [
            [
              11,
              "MW",
              "226 Wohlers Hall",
              9,
              [
                "Grimsley, K"
              ],
              -1,
              -1,
              -1
            ]
          ],
          1,
          0,
          0,
          [],
          -1
        ]
      },
      [],
      "The Real Estate Finance Academy prepares students for careers within the real estate industry. Topics include real estate financial modeling, investment case studies, underwriting real estate markets, and developing professional communication skills. Students who choose to repeat the course assume leadership roles over time.",
      []
    ],
    "FIN 416": [
      "Applied Derivative Strategies",
      {
        "E5": [
          "76375",
          [
            [
              13,
              "TR",
              "2007 Business Instructional Fac",
              16,
              [
                "Excell, R"
              ],
              -1,
              -1,
              -1
            ]
          ],
          3,
          0,
          0,
          [],
          -1
        ]
      },
      [],
      "Building upon the basic options knowledge gained in FIN 412, this course covers volatility trading looking not only at the CBOE VIX product and OTC variance swaps, but also the application of volatility trading across all asset classes with listed products. The most topical options and derivatives structures such as risk parity, risk premia capture, alternative risk premia and volatility targeting are explored at the conclusion of the course.",
      []
    ],
    "FIN 394": [
      "Women in Finance Academy",
      {
        "H2": [
          "71621",
          [
            [
              54,
              "W",
              "2063 Business Instructional Fac",
              16,
              [
                "Hart, J"
              ],
              -1,
              -1,
              -1
            ]
          ],
          1,
          0,
          0,
          [],
          -1
        ]
      },
      [],
      "Given the unique challenges women face in the business world, this course provides the tools for women to thrive in careers in finance. The course includes a mentoring program, soft and technical skills development, panel discussions with women leaders, and networking opportunities. Admission by application process in the prior semester.",
      []
    ],
    "FIN 415": [
      "Fixed Income Portfolios",
      {
        "UG1": [
          "62218",
          [
            [
              0,
              "TR",
              "3039 Business Instructional Fac",
              16,
              [
                "Widdicks, M"
              ],
              -1,
              -1,
              -1
            ]
          ],
          3,
          0,
          0,
          [],
          -1
        ]
      },
      [],
      "Conceptual foundations and implementation of strategies for the selection, evaluation, and revision of portfolios of fixed-income financial assets (bonds).",
      []
    ],
    "FIN 419": [
      "Real Client Managed Portfolios",
      {
        "P1": [
          "32653",
          [
            [
              2,
              "TR",
              "2041 Business Instructional Fac",
              16,
              [
                "Excell, R"
              ],
              -1,
              -1,
              -1
            ]
          ],
          3,
          0,
          0,
          [],
          -1
        ]
      },
      [],
      "Applies academic topics on financial markets, security analysis/valuation and portfolio management to hands-on investment management. Students will form and review objectives, constraints, and investment policy as it relates to the client's money under management. They will purchase securities, monitor performance of the portfolio, and make recommendations for any adjustments to the holdings. They will be fully educated and responsible to the fiduciary and ethical standards of professional money management as guided by the CFA Institute.",
      []
    ],
    "FIN 423": [
      "Entrepreneurial Finance",
      {
        "F1": [
          "32621",
          [
            [
              13,
              "TR",
              "240 Wohlers Hall",
              9,
              [
                "Krueger, G"
              ],
              -1,
              -1,
              -1
            ]
          ],
          4,
          0,
          0,
          [],
          -1
        ],
        "F2": [
          "32617",
          [
            [
              26,
              "TR",
              "240 Wohlers Hall",
              9,
              [
                "Krueger, G"
              ],
              -1,
              -1,
              -1
            ]
          ],
          4,
          0,
          0,
          [],
          -1
        ]
      },
      [],
      "The study of the financial side of entrepreneurial firms, including alternative methods of organization, sources of financing, use of financial statements as a management tool, financial planning, valuation methods, and exit strategies, all from the perspective of an owner, CEO or CFO.",
      []
    ],
    "FIN 434": [
      "Employee Benefit Plans",
      {
        "R3": [
          "51223",
          [
            [
              0,
              "TR",
              "245 Wohlers Hall",
              9,
              [
                "Raskie, S"
              ],
              -1,
              -1,
              -1
            ]
          ],
          3,
          0,
          0,
          [],
          -1
        ]
      },
      [],
      "Studies the purpose, structure, and financial aspects of employee benefit plans, including pensions, health insurance, life insurance, and disability plans.",
      []
    ],
    "FIN 425": [
      "Private Equity/Venture Capital",
      {
        "SL1": [
          "55582",
          [
            [
              25,
              "TR",
              "1025 Business Instructional Fac",
              16,
              [
                "Lagaras, S"
              ],
              -1,
              -1,
              -1
            ]
          ],
          3,
          0,
          0,
          [],
          -1
        ]
      },
      [],
      "Provides students with an understanding of the nature of the private equity market, the principal participants in this market, and how they function.",
      []
    ],
    "FIN 424": [
      "Mergers and Acquisition",
      {
        "C": [
          "55581",
          [
            [
              0,
              "MW",
              "3041 Business Instructional Fac",
              16,
              [
                "Almeida, H"
              ],
              -1,
              -1,
              -1
            ]
          ],
          3,
          0,
          0,
          [],
          -1
        ]
      },
      [],
      "Focuses on identifying ways to increase firm value through mergers and acquisitions (M&A) and corporate restructurings. Surveys the drivers of success (failure) in M&A transactions and develop your skills in the design and evaluation of transactions.",
      []
    ],
    "FIN 435": [
      "Personal Wealth Management",
      {
        "ONL": [
          "55583",
          [
            [
              12,
              "",
              "ONLINE",
              7,
              [
                "Brown, D"
              ],
              -1,
              -1,
              -1
            ]
          ],
          3,
          3,
          0,
          [],
          -1
        ],
        "P": [
          "63568",
          [
            [
              2,
              "TR",
              "245 Wohlers Hall",
              9,
              [
                "Raskie, S"
              ],
              -1,
              -1,
              -1
            ]
          ],
          3,
          0,
          0,
          [],
          -1
        ],
        "WM1": [
          "77684",
          [
            [
              2,
              "MW",
              "1025 Business Instructional Fac",
              16,
              [
                "Fonseca, J"
              ],
              -1,
              -1,
              -1
            ]
          ],
          3,
          0,
          0,
          [],
          -1
        ]
      },
      [],
      "Studies personal wealth management techniques with an emphasis on life insurance products; covers life insurance policies, annuities, trusts, buy-sell arrangements, investing in stocks, bonds and mutual funds, banking and barrowing, purchasing residential and commercial real estate, income and estate taxation and management of personal financial portfolio.",
      []
    ],
    "FIN 463": [
      "Investment Banking",
      {
        "B1": [
          "65036",
          [
            [
              13,
              "TR",
              "243 Wohlers Hall",
              9,
              [
                "Bertram, J"
              ],
              -1,
              -1,
              -1
            ]
          ],
          3,
          0,
          0,
          [],
          -1
        ],
        "B2": [
          "74073",
          [
            [
              0,
              "TR",
              "1049 Business Instructional Fac",
              16,
              [
                "Bertram, J"
              ],
              -1,
              -1,
              -1
            ]
          ],
          3,
          0,
          0,
          [],
          -1
        ]
      },
      [],
      "The mechanics of financial statement analysis and ratio analysis; development of investment banking/corporate finance valuation models (including DCF, leveraged buyout and merger models) in order to determine the intrinsic value of companies and price investment banking deals.",
      []
    ],
    "FIN 443": [
      "Legal Issues in Real Estate",
      {
        "P3": [
          "46750",
          [
            [
              11,
              "MW",
              "1025 Business Instructional Fac",
              16,
              [
                "Perkins, S"
              ],
              -1,
              -1,
              -1
            ]
          ],
          4,
          0,
          0,
          [],
          -1
        ]
      },
      [],
      "Overview of legal concepts, issues, and principles involving real estate.",
      []
    ],
    "FIN 446": [
      "Real Estate Financial Markets",
      {
        "AR1": [
          "63631",
          [
            [
              0,
              "MW",
              "1049 Business Instructional Fac",
              16,
              [
                "Sehy, A"
              ],
              -1,
              -1,
              -1
            ]
          ],
          3,
          0,
          0,
          [],
          -1
        ]
      },
      [],
      "Discusses real estate financing techniques and the secondary market for real estate financial assets including residential and commercial mortgage-backed securities (RMBS and CMBS).",
      []
    ],
    "FIN 464": [
      "Applied Financial Analysis",
      {
        "U1": [
          "61872",
          [
            [
              25,
              "TR",
              "2007 Business Instructional Fac",
              16,
              [
                "Vitek, M"
              ],
              -1,
              -1,
              -1
            ]
          ],
          4,
          0,
          0,
          [],
          -1
        ],
        "U2": [
          "61873",
          [
            [
              2,
              "TR",
              "2007 Business Instructional Fac",
              16,
              [
                "Vitek, M"
              ],
              -1,
              -1,
              -1
            ]
          ],
          4,
          0,
          0,
          [],
          -1
        ]
      },
      [],
      "Provides key building blocks necessary for many careers in finance. Designed to provide a practical approach to analyzing and interpreting complex financial statements to make decisions from a range of user perspectives, including investment banks, equity investors and commercial banks. Advanced financial analysis and forecasting will be applied through assignments and casework. There will be an emphasis on business writing skills commonly applied by finance professionals.",
      []
    ],
    "FIN 461": [
      "Banking and Financial Regulation",
      {
        "F": [
          "32604",
          [
            [
              0,
              "TR",
              "241 Wohlers Hall",
              9,
              [
                "Manouchehri Irani, R"
              ],
              -1,
              -1,
              -1
            ]
          ],
          3,
          0,
          0,
          [],
          -1
        ]
      },
      [],
      "Survey of the structure, functions, regulation, and risk management activities of banks and nonbank financial institutions; central banking and monetary policy effects on financial institutions.",
      []
    ],
    "FIN 494": [
      "Senior Research",
      {
        "": [
          "10111",
          [
            [
              12,
              "",
              "ONLINE",
              7,
              [
                "Staff"
              ],
              -1,
              -1,
              -1
            ]
          ],
          4,
          4,
          0,
          [],
          -1
        ]
      },
      [],
      "Research and reading course for students concentrating in finance, insurance, urban land economics, or related areas who meet one of the following requirements: (1) have a cumulative grade-point average of 3. 0 or better; (2) have attained Honors Day recognition in the junior year; or (3) have consent of instructor. May be taken by students in the college honors program in partial fulfillment of the honors requirements.",
      []
    ],
    "FIN 495": [
      "Senior Research",
      {
        "": [
          "10115",
          [
            [
              12,
              "",
              "ONLINE",
              7,
              [
                "Staff"
              ],
              -1,
              -1,
              -1
            ]
          ],
          4,
          4,
          0,
          [],
          -1
        ]
      },
      [],
      "Research and reading course for students concentrating in finance, insurance, urban land economics, or related areas. May be taken by students in the college honors program in partial fulfillment of the honors requirements.",
      []
    ],
    "FIN 500": [
      "Introduction to Finance",
      {
        "IMB": [
          "71632",
          [
            [
              12,
              "",
              "ONLINE",
              7,
              [
                "Satchell, J"
              ],
              -1,
              -1,
              -1
            ]
          ],
          4,
          3,
          0,
          [],
          -1
        ],
        "MSF": [
          "57216",
          [
            [
              11,
              "MW",
              "2011 Business Instructional Fac",
              16,
              [
                "Smith, M"
              ],
              -1,
              -1,
              -1
            ]
          ],
          4,
          0,
          0,
          [],
          -1
        ],
        "MSP": [
          "53227",
          [
            [
              26,
              "TR",
              "1025 Business Instructional Fac",
              16,
              [
                "Marcinkowski, M"
              ],
              -1,
              -1,
              -1
            ]
          ],
          4,
          0,
          0,
          [],
          -1
        ],
        "ONL": [
          "71633",
          [
            [
              12,
              "",
              "ONLINE",
              7,
              [
                "Satchell, J"
              ],
              -1,
              -1,
              -1
            ]
          ],
          4,
          3,
          0,
          [],
          -1
        ]
      },
      [],
      "Introduction to financial management and decision making. A customized course, designed to provide a survey of finance for graduate students who do not necessarily have previous training in the disciplines. Different sections of the course will cover different sets of topics.",
      []
    ],
    "FIN 501": [
      "Financial Economics",
      {
        "M1": [
          "71624",
          [
            [
              0,
              "TR",
              "3063 Business Instructional Fac",
              16,
              [
                "Alston, M"
              ],
              -1,
              -1,
              -1
            ]
          ],
          4,
          0,
          0,
          [],
          -1
        ]
      },
      [],
      "A firm's long-run value ultimately depends on its business fundamentals. This course covers micro- and macro-economic drivers of such fundamentals, such as consumer demand, market competitiveness, government regulation, interest rates, business cycles, and monetary policy. Also includes topics in risk and intertemporal decision-making.",
      []
    ],
    "FIN 511": [
      "Investments",
      {
        "S1": [
          "40486",
          [
            [
              25,
              "TR",
              "2041 Business Instructional Fac",
              16,
              [
                "Spencer, X"
              ],
              -1,
              -1,
              -1
            ]
          ],
          4,
          0,
          0,
          [],
          -1
        ]
      },
      [],
      "Introduction to investment analysis, including the theory and implementation of portfolio theory; empirical evidence on the performance of financial assets; evaluation of portfolio investment strategies; and the extension of diversification to international markets.",
      []
    ],
    "FIN 502": [
      "Quantitative Finance",
      {
        "QA": [
          "71630",
          [
            [
              0,
              "MW",
              "2001 Business Instructional Fac",
              16,
              [
                "Pae, T"
              ],
              -1,
              -1,
              -1
            ]
          ],
          4,
          0,
          0,
          [],
          -1
        ]
      },
      [],
      "Quantitative methods used for financial decision making. Topics include elements of statistics, mathematics, and specific analytical tools used in the study and practice of finance.",
      []
    ],
    "FIN 513": [
      "Advanced Financial Derivatives",
      {
        "FFE": [
          "40796",
          [
            [
              25,
              "TR",
              "3063 Business Instructional Fac",
              16,
              [
                "Widdicks, M"
              ],
              -1,
              -1,
              -1
            ]
          ],
          4,
          0,
          0,
          [],
          -1
        ]
      },
      [],
      "Provides an introduction to modern techniques for pricing options, swaps, and related financial instruments; the use of such instruments in managing financial risk; and the measurement and management of their risks.",
      []
    ],
    "FIN 512": [
      "Financial Derivatives",
      {
        "SF": [
          "40794",
          [
            [
              2,
              "TR",
              "2005 Business Instructional Fac",
              16,
              [
                "Kargar, M"
              ],
              -1,
              -1,
              -1
            ]
          ],
          4,
          0,
          0,
          [],
          -1
        ]
      },
      [],
      "Introduction to options, futures, swaps and other derivative securities; examination of institutional aspects of the markets; theories of pricing; discussion of simple as well as complicated trading strategies (arbitrage, hedging, and spread); applications for asset and risk management.",
      []
    ],
    "FIN 503": [
      "Quantitative Finance II",
      {
        "Q2": [
          "71631",
          [
            [
              0,
              "MW",
              "2001 Business Instructional Fac",
              16,
              [
                "Pae, T"
              ],
              -1,
              -1,
              -1
            ]
          ],
          2,
          0,
          0,
          [],
          -1
        ]
      },
      [],
      "This course covers topics in time series analysis with an emphasis on applications. It is intended to prepare MSF students for more advanced courses in finance. This course provides some basic knowledge of financial time series data. It also introduces models and methods widely used by academics and practitioners. The purpose of this course is to understand proper use and limitations of econometric methods in applied time series analysis.",
      []
    ],
    "FIN 515": [
      "Fixed Income Portfolios",
      {
        "GR1": [
          "43777",
          [
            [
              0,
              "TR",
              "3039 Business Instructional Fac",
              16,
              [
                "Widdicks, M"
              ],
              -1,
              -1,
              -1
            ]
          ],
          4,
          0,
          0,
          [],
          -1
        ]
      },
      [],
      "Conceptual foundations and implementation of strategies for the selection, evaluation, and revision of portfolios of fixed-income financial assets (bonds); examination of related research.",
      []
    ],
    "FIN 504": [
      "Accounting for Financial Analysis",
      {
        "FA1": [
          "71622",
          [
            [
              13,
              "TR",
              "241 Wohlers Hall",
              9,
              [
                "Vitek, M"
              ],
              -1,
              -1,
              -1
            ]
          ],
          2,
          0,
          0,
          [],
          -1
        ]
      },
      [],
      "This course will develop an understanding of the most fundamental accounting concepts and provide key building blocks necessary for intermediate and advanced financial statement analysis. It is designed to provide a basic but practical application of financial analyses commonly performed by industry professionals.",
      []
    ],
    "FIN 518": [
      "Financial Modeling",
      {
        "FM2": [
          "62374",
          [
            [
              2,
              "MW",
              "1049 Business Instructional Fac",
              16,
              [
                "Kennemore, D"
              ],
              -1,
              -1,
              -1
            ]
          ],
          4,
          0,
          0,
          [],
          -1
        ],
        "FM4": [
          "75506",
          [
            [
              11,
              "MW",
              "3039 Business Instructional Fac",
              16,
              [
                "Kennemore, D"
              ],
              -1,
              -1,
              -1
            ]
          ],
          4,
          0,
          0,
          [],
          -1
        ]
      },
      [],
      "The objective is to learn the fundamentals and practice building financial models using Microsoft Excel. By the end of the term, each student should be able to develop an understanding of any financial relationship and build that financial relationship into a model using the built-in function of Excel. Financial modeling, by definition, requires significant work outside of the classroom. Models are introduced, demonstrated, and reviewed in class, but each student is expected to research and collect data, and to construct the models, prior to each week's class meeting.",
      []
    ],
    "FIN 521": [
      "Advanced Corporate Finance",
      {
        "G": [
          "65426",
          [
            [
              13,
              "MW",
              "240 Wohlers Hall",
              9,
              [
                "Xu, Q"
              ],
              -1,
              -1,
              -1
            ]
          ],
          4,
          0,
          0,
          [],
          -1
        ]
      },
      [],
      "Addresses both the theoretical and applied aspects of firms' financing decisions; topics include capital structure and cost of capital theories; mergers, acquisitions and leveraged buyouts; options, warrants, and convertibles; venture capital and initial public offerings; and pensions.",
      []
    ],
    "FIN 526": [
      "Investment Banking",
      {
        "B2": [
          "74064",
          [
            [
              13,
              "TR",
              "243 Wohlers Hall",
              9,
              [
                "Bertram, J"
              ],
              -1,
              -1,
              -1
            ]
          ],
          4,
          0,
          0,
          [],
          -1
        ]
      },
      [],
      "Provides key building blocks necessary for a career in investment banking, valuation and other related fields. It is designed to provide a practical application of financial statement analysis, modeling, valuation, and presentation skills commonly performed by industry professionals.",
      []
    ],
    "FIN 535": [
      "Wealth Management",
      {
        "WM2": [
          "77683",
          [
            [
              0,
              "MW",
              "1025 Business Instructional Fac",
              16,
              [
                "Fonseca, J"
              ],
              -1,
              -1,
              -1
            ]
          ],
          4,
          0,
          0,
          [],
          -1
        ]
      },
      [],
      "This course studies personal wealth management techniques with an emphasis on life insurance products; covers life insurance policies, annuities, trusts, buy-sell arrangements, investing in stocks, bonds and mutual funds, banking and borrowing, purchasing residential and commercial real estate, income and estate taxation and management of personal financial portfolio. The course also allows students to build a wealth management plan based on a case scenario.",
      []
    ],
    "FIN 527": [
      "Mergers & Acquisitions Topics",
      {
        "C": [
          "65672",
          [
            [
              0,
              "MW",
              "3041 Business Instructional Fac",
              16,
              [
                "Almeida, H"
              ],
              -1,
              -1,
              -1
            ]
          ],
          4,
          0,
          0,
          [],
          -1
        ]
      },
      [],
      "Focuses on identifying ways to increase firm value through mergers and acquisitions (M&A) and corporate restructurings. We will develop your skills in the design and evaluation of transactions. Specific topics addressed in the course are the valuation of companies, structuring of transactions, deal tactics and strategy, valuation of leveraged buyouts, and spin-offs/carve-outs. We will also delve into issues of law, accounting and taxation and how they affect the structuring and outcome of merger transactions. Knowledge about M&A is an important component of any corporate finance professional and is the foundation for effective work in a wide range of fields including corporate development, investment banking, consulting, and advising senior management.",
      []
    ],
    "FIN 543": [
      "Legal Issues in Real Estate",
      {
        "P4": [
          "70715",
          [
            [
              11,
              "MW",
              "1025 Business Instructional Fac",
              16,
              [
                "Perkins, S"
              ],
              -1,
              -1,
              -1
            ]
          ],
          4,
          0,
          0,
          [],
          -1
        ]
      },
      [],
      "This course examines the fundamentals of real estate from a legal perspective. Students develop skills in using legal concepts in a real estate transactional setting that incorporates traditional course materials, case studies, real life transactions, and guest lectures designed to provide a practical \"hands-on\" approach to real estate law. We explore a broad range of current sophisticated real estate transactions relating to residential and commercial purchases, sales, leasehold interests, common interest communities, ownership, financing, brokerage, land use and development. We discuss the legal implications that contractual private and legislative public restrictions have on individuals' real property rights and discuss public policy arguments related to private owners legal rights.",
      []
    ],
    "FIN 529": [
      "Applied Financial Analysis",
      {
        "G1": [
          "74074",
          [
            [
              25,
              "TR",
              "2007 Business Instructional Fac",
              16,
              [
                "Vitek, M"
              ],
              -1,
              -1,
              -1
            ]
          ],
          4,
          0,
          0,
          [],
          -1
        ],
        "G2": [
          "74075",
          [
            [
              2,
              "TR",
              "2007 Business Instructional Fac",
              16,
              [
                "Vitek, M"
              ],
              -1,
              -1,
              -1
            ]
          ],
          4,
          0,
          0,
          [],
          -1
        ]
      },
      [],
      "Provides key building blocks necessary for many careers in finance. Designed to provide a practical approach to analyzing and interpreting complex financial statements to make decisions from a range of user perspectives, including investment banks, equity investors and commercial banks. Advanced financial analysis and forecasting will be applied through assignments and casework. There will be an emphasis on business writing skills commonly applied by finance professionals.",
      []
    ],
    "FIN 537": [
      "Financial Risk Management",
      {
        "C": [
          "74070",
          [
            [
              0,
              "MW",
              "241 Wohlers Hall",
              9,
              [
                "Pearson, N"
              ],
              -1,
              -1,
              -1
            ]
          ],
          4,
          0,
          0,
          [],
          -1
        ],
        "D": [
          "74071",
          [
            [
              2,
              "MW",
              "241 Wohlers Hall",
              9,
              [
                "Pearson, N"
              ],
              -1,
              -1,
              -1
            ]
          ],
          4,
          0,
          0,
          [],
          -1
        ]
      },
      [],
      "Covers selected topics in financial risk management. The focus is on statistical techniques used in financial risk management rather than risk management practice, cases, or valuation issues. The course will cover the value-at-risk (VaR) measure and expected shortfall, statistical techniques useful to model financial market returns, and techniques used to model the joint distribution of defaults on fixed income instruments. The course will also cover additional topics such as retail credit risk, risk budgeting, and economic capital modelling.",
      []
    ],
    "FIN 536": [
      "Banking and Financial Regulation",
      {
        "A": [
          "62363",
          [
            [
              0,
              "TR",
              "241 Wohlers Hall",
              9,
              [
                "Manouchehri Irani, R"
              ],
              -1,
              -1,
              -1
            ]
          ],
          4,
          0,
          0,
          [],
          -1
        ]
      },
      [],
      "Survey of the structure, functions, regulation, and risk management activities of banks and nonbank financial institutions; central banking and monetary policy effects on financial institutions.",
      []
    ],
    "FIN 546": [
      "Real Estate Financial Markets",
      {
        "AR2": [
          "78015",
          [
            [
              0,
              "MW",
              "1049 Business Instructional Fac",
              16,
              [
                "Sehy, A"
              ],
              -1,
              -1,
              -1
            ]
          ],
          4,
          0,
          0,
          [],
          -1
        ]
      },
      [],
      "This is an applied course in real estate investment that focuses on the U.S. mortgage and asset-backed securities markets. The course will review the multi-trillion dollar mortgage and asset-backed bond markets. We will discuss the fundamentals of securitization, and strategies to structure deals. We will also consider real estate investment trusts (REITs), collateralized debt obligations (CDOs) and credit default swaps (CDS). The course will develop analytical skills in deal structuring and pricing, and offer all students an opportunity to develop their business skills through case discussions.",
      []
    ],
    "FIN 551": [
      "International Finance",
      {
        "C": [
          "40802",
          [
            [
              11,
              "TR",
              "2007 Business Instructional Fac",
              16,
              [
                "Chan, K"
              ],
              -1,
              -1,
              -1
            ]
          ],
          4,
          0,
          0,
          [],
          -1
        ]
      },
      [],
      "Explores the characteristics of the international financial market and examines various aspects of corporate financial management. Topics may include international parity conditions, exchange rate risk management, country risk, cross-border investment analysis, multi national firm budgeting, hedging in foreign currency markets, accessing international financial markets for financing, and competitive strategy in a global marketplace.",
      []
    ],
    "FIN 557": [
      "Financial Data Management and Analysis",
      {
        "FD1": [
          "74140",
          [
            [
              11,
              "TR",
              "2020 Wymer Hall",
              7,
              [
                "Gao, X"
              ],
              -1,
              -1,
              -1
            ]
          ],
          4,
          0,
          0,
          [],
          -1
        ],
        "FD2": [
          "74141",
          [
            [
              2,
              "TR",
              "3007 Business Instructional Fac",
              16,
              [
                "Gao, X"
              ],
              -1,
              -1,
              -1
            ]
          ],
          4,
          0,
          0,
          [],
          -1
        ]
      },
      [],
      "Proper data handling and management is essential to the success of data analysis. The primary goal of this course is to learn principles and practices of data management with an emphasis on working with financial databases. Students will gain practical skills in data storage, data preparation, and data extractions that eventually lead to data analysis. Data management procedures including SQL queries, and data analysis techniques using large-scale statistical software are presented.",
      []
    ],
    "FIN 558": [
      "Data Science and Python for Finance",
      {
        "P1": [
          "75520",
          [
            [
              22,
              "F",
              "3007 Business Instructional Fac",
              16,
              [
                "Pae, T"
              ],
              -1,
              -1,
              -1
            ]
          ],
          2,
          0,
          0,
          [],
          -1
        ]
      },
      [],
      "Focuses on introducing Python for financial analysis. It provides a detailed understanding of Python basics. Students will apply Python in solving problems in corporate finance and performing investment analysis. Topics include capital budgeting decisions, equity valuation, risk and return, portfolio optimization, and technical trading strategies.",
      []
    ],
    "FIN 550": [
      "Big Data Analytics in Finance for Predictive and Causal Analysis",
      {
        "BA2": [
          "74066",
          [
            [
              13,
              "TR",
              "2020 Wymer Hall",
              7,
              [
                "Gao, X",
                "Stechuk, S"
              ],
              -1,
              -1,
              -1
            ]
          ],
          4,
          0,
          0,
          [],
          -1
        ],
        "BD3": [
          "74068",
          [
            [
              2,
              "MW",
              "3041 Business Instructional Fac",
              16,
              [
                "Molitor, D",
                "Stechuk, S"
              ],
              -1,
              -1,
              -1
            ]
          ],
          4,
          0,
          0,
          [],
          -1
        ]
      },
      [],
      "Examines methods in big data analytics for financial and economic analysis. Students design and conduct independent empirical research using tools such as machine learning, regression, randomized trials, and quasi-experiments. Emphasis is on distinguishing correlation from causation, developing reproducible workflows, and critically evaluating analytic strategies. Prepares students for advanced professional and research roles requiring independent judgment and defense of methodological choices in data-rich environments.",
      []
    ],
    "FIN 573": [
      "Applications of Investment Banking Concepts",
      {
        "IMB": [
          "74408",
          [
            [
              12,
              "",
              "ONLINE",
              7,
              [
                "Bertram, J",
                "Metzger, R"
              ],
              -1,
              -1,
              -1
            ]
          ],
          4,
          3,
          0,
          [],
          -1
        ],
        "ONL": [
          "74409",
          [
            [
              12,
              "",
              "ONLINE",
              7,
              [
                "Bertram, J",
                "Metzger, R"
              ],
              -1,
              -1,
              -1
            ]
          ],
          4,
          3,
          0,
          [],
          -1
        ]
      },
      [],
      "Will build off the core topics explored in FIN 572, The Finance of Mergers and Acquisitions and ACCY 532, Accounting for Mergers and Acquisitions and Other Complex Transactions. It is designed to provide a practical application of financial statement analysis, modeling, and valuation. The course covers the mechanics of financial statement analysis, ratio analysis, and financial model building. The course will also focus on applying the financial statements and forecasts within the context of company valuation, utilizing common industry techniques. Prerequisite: It is recommended that students have a grasp of core accounting principles and have a basic knowledge of concepts in finance (time value of money, etc.). It is also recommended that students complete ACCY 532 and FIN 572 (or equivalents) before enrolling in this course.",
      []
    ],
    "FIN 571": [
      "Money and Banking",
      {
        "IMB": [
          "73008",
          [
            [
              12,
              "",
              "ONLINE",
              7,
              [
                "Dolgopolov, V",
                "Manouchehri Irani, R",
                "Meisenzahl, R"
              ],
              -1,
              -1,
              -1
            ]
          ],
          4,
          3,
          0,
          [],
          -1
        ],
        "ONL": [
          "73009",
          [
            [
              12,
              "",
              "ONLINE",
              7,
              [
                "Dolgopolov, V",
                "Manouchehri Irani, R",
                "Meisenzahl, R"
              ],
              -1,
              -1,
              -1
            ]
          ],
          4,
          3,
          0,
          [],
          -1
        ]
      },
      [],
      "This online course will provide you with a framework that can be used to understand the connections between money, banking, and financial markets, as well as the implementation and impacts of modern monetary policy. Upon completion of this course, you will be able to apply this framework to assess how new developments in finance and public policy may influence the macroeconomic and business environment.",
      []
    ],
    "FIN 570": [
      "Corporate Finance",
      {
        "IMB": [
          "74062",
          [
            [
              12,
              "",
              "ONLINE",
              7,
              [
                "Almeida, H",
                "Spencer, X",
                "Zeume, S"
              ],
              -1,
              -1,
              -1
            ]
          ],
          4,
          3,
          0,
          [],
          -1
        ],
        "ONL": [
          "74063",
          [
            [
              12,
              "",
              "ONLINE",
              7,
              [
                "Almeida, H",
                "Spencer, X",
                "Zeume, S"
              ],
              -1,
              -1,
              -1
            ]
          ],
          4,
          3,
          0,
          [],
          -1
        ]
      },
      [],
      "You will learn how to use key finance principles to understand and measure business success as well as identify and promote true value creation. You will also learn financial management tools that allow us to determine the optimal financing and risk management strategies for corporations. In the first part of the course, you will learn how to use accounting information to form key financial ratios to measure a companys financial health and to manage a company's short-term and long-term liquidity needs. You will also learn how to use valuation techniques to make sound business investment and acquisition decisions. Finally, you will learn how to incorporate risk and uncertainty into investment decisions and evaluate the performance of existing investments. In the second part of the course, you will learn how companies choose how much debt to have and which type of debt to issue. You will also learn how payout decisions (dividends and share repurchases) affect firm value and how to determine a companys optimal payout policy. Finally, you will learn how to use risk management tools, such as derivatives, and liquidity to mitigate specific risks, such as currency risk. You will apply these tools to develop a financial management framework for M&A decisions, and R&D investments.",
      []
    ],
    "FIN 575": [
      "Investments & Performance Evaluation",
      {
        "IMB": [
          "78032",
          [
            [
              12,
              "",
              "ONLINE",
              7,
              [
                "Gao, X",
                "Pollet, J",
                "Spencer, X"
              ],
              -1,
              -1,
              -1
            ]
          ],
          4,
          3,
          0,
          [],
          -1
        ],
        "ONL": [
          "78033",
          [
            [
              12,
              "",
              "ONLINE",
              7,
              [
                "Gao, X",
                "Pollet, J",
                "Spencer, X"
              ],
              -1,
              -1,
              -1
            ]
          ],
          4,
          3,
          0,
          [],
          -1
        ]
      },
      [],
      "We analyze the trade-off between risk and expected return along with portfolio choice, performance evaluation, and security pricing. We use the Capital Asset Pricing Model (CAPM) and multi-factor models to evaluate the performance of various securities and portfolios. We establish benchmark returns for securities and apply firm valuation techniques. We discuss market efficiency and its implications. We apply these techniques to the performance of mutual funds, hedge funds, and strategies designed to earn risk-adjusted returns.",
      []
    ],
    "FIN 574": [
      "Microeconomics for Business",
      {
        "IMB": [
          "74807",
          [
            [
              12,
              "",
              "ONLINE",
              7,
              [
                "Brown, J",
                "Dolgopolov, V",
                "Miller, N"
              ],
              -1,
              -1,
              -1
            ]
          ],
          4,
          3,
          0,
          [],
          -1
        ],
        "ONL": [
          "74808",
          [
            [
              12,
              "",
              "ONLINE",
              7,
              [
                "Brown, J",
                "Dolgopolov, V",
                "Miller, N"
              ],
              -1,
              -1,
              -1
            ]
          ],
          4,
          3,
          0,
          [],
          -1
        ]
      },
      [],
      "Microeconomics for professional business students. Shows relevance of value and distribution theories for business managers. Includes demand and supply theory, consumer choice, production and cost theory, industrial structure, and wage and capital theory. Intended for students in the Master of Business Administration program.",
      []
    ],
    "FIN 580": [
      "Special Topics in Finance",
      {
        "ETA": [
          "69358",
          [
            [
              114,
              "MW",
              "2043 Business Instructional Fac",
              16,
              [
                "Smith, M"
              ],
              -1,
              -1,
              -1
            ]
          ],
          4,
          0,
          0,
          [],
          -1
        ],
        "INT": [
          "66148",
          [
            [
              12,
              "",
              "ONLINE",
              7,
              [
                "Lucht, K",
                "Widdicks, M"
              ],
              -1,
              -1,
              -1
            ]
          ],
          4,
          18,
          0,
          [],
          -1
        ],
        "PHD": [
          "47517",
          [
            [
              40,
              "F",
              "243 Wohlers Hall",
              9,
              [
                "Huang, J",
                "Lucht, K"
              ],
              -1,
              -1,
              -1
            ]
          ],
          4,
          11,
          0,
          [],
          -1
        ],
        "QI2": [
          "69623",
          [
            [
              1,
              "F",
              "240 Wohlers Hall",
              9,
              [
                "Zhang, Q"
              ],
              -1,
              -1,
              -1
            ]
          ],
          4,
          0,
          0,
          [],
          -1
        ],
        "SL2": [
          "65773",
          [
            [
              11,
              "TR",
              "174 Wohlers Hall",
              9,
              [
                "Lagaras, S"
              ],
              -1,
              -1,
              -1
            ]
          ],
          4,
          0,
          0,
          [],
          -1
        ]
      },
      [],
      "Lectures and discussions relating to new areas of interest. See class schedule for topics and prerequisites.",
      []
    ],
    "FIN 586": [
      "MSF Academy II",
      {
        "P": [
          "77699",
          [
            [
              11,
              "TR",
              "1029C Business Instructional Fac",
              7,
              [
                "Morris, M"
              ],
              -1,
              -1,
              -1
            ]
          ],
          2,
          0,
          0,
          [],
          -1
        ]
      },
      [],
      "MSF Academy II builds upon the skills learned in MSF Academy I by focusing within a specific area of the finance industry.",
      []
    ],
    "FIN 589": [
      "Applied Portfolio Management",
      {
        "P2": [
          "74144",
          [
            [
              2,
              "TR",
              "2041 Business Instructional Fac",
              16,
              [
                "Excell, R"
              ],
              -1,
              -1,
              -1
            ]
          ],
          4,
          0,
          0,
          [],
          -1
        ]
      },
      [],
      "Applies academic topics on financial markets, security analysis/valuation and portfolio management to hands-on investment management. Students will form and review objectives, constraints, and investment policy as it relates to the client's money under management. They will purchase securities, monitor performance of the portfolio, and make recommendations for any adjustments to the holdings. They will be fully educated and responsible for the fiduciary and ethical standards of professional money management as guided by the CFA Institute.",
      []
    ],
    "FIN 583": [
      "Practicum",
      {
        "MT1": [
          "71627",
          [
            [
              12,
              "",
              "ONLINE",
              7,
              [
                "Thanos, M"
              ],
              -1,
              -1,
              -1
            ]
          ],
          4,
          18,
          0,
          [],
          -1
        ]
      },
      [],
      "A semester-long, typically corporate-sponsored, team project for MSFE and MSF students that is usually completed by the end of the third semester of study. The goals of the Practicum are: a) to use learned or new tools on real world projects of interest to the corporate sponsor; b) to replicate as closely as possible the environment of the working world where students will soon find themselves employed; c) to work cohesively with other members of a team so as to efficiently produce the desired project results; and d) to be able to communicate effectively with technical and non-technical audiences, which may include the sponsor and/or co-workers.",
      []
    ],
    "FIN 595": [
      "Empirical Corporate Finance",
      {
        "L1": [
          "76376",
          [
            [
              82,
              "T",
              "ARR Business Instructional Fac",
              7,
              [
                "Lagaras, S"
              ],
              -1,
              -1,
              -1
            ]
          ],
          4,
          0,
          0,
          [],
          -1
        ]
      },
      [],
      "This seminar will study recent research in corporate finance that uses modern empirical methods to focus on causal inference. Students will be required to write a research proposal. The objective is to sharpen students' skills as consumers and producers of empirical corporate finance. This seminar is also beneficial for researchers in related fields such as credit markets and banking, asset pricing, financial accounting and applied microeconomics.",
      []
    ],
    "FIN 590": [
      "Individual Study and Research",
      {
        "": [
          "10127",
          [
            [
              12,
              "",
              "ONLINE",
              7,
              [
                "Staff"
              ],
              -1,
              -1,
              -1
            ]
          ],
          4,
          4,
          0,
          [],
          -1
        ],
        "SEM": [
          "40359",
          [
            [
              13,
              "TR",
              "3039 Business Instructional Fac",
              16,
              [
                "Pollet, J"
              ],
              -1,
              -1,
              -1
            ]
          ],
          4,
          0,
          0,
          [],
          -1
        ]
      },
      [],
      "Directed reading and research.",
      []
    ],
    "FIN 599": [
      "Thesis Research",
      {
        "1": [
          "10129",
          [
            [
              12,
              "",
              "ONLINE",
              7,
              [
                "Staff"
              ],
              -1,
              -1,
              -1
            ]
          ],
          16,
          4,
          0,
          [],
          -1
        ]
      },
      [],
      "Required for those writing master's and doctoral theses in finance.",
      []
    ]
  },
  "caches": {
    "periods": [
      "1100 - 1220",
      "1400 - 1650",
      "0930 - 1050",
      "0900 - 0950",
      "1000 - 1050",
      "1100 - 1150",
      "1200 - 1250",
      "1300 - 1350",
      "1400 - 1450",
      "1600 - 1715",
      "0930 - 1045",
      "1230 - 1350",
      "ARRANGED",
      "1400 - 1520",
      "1400 - 1550",
      "1500 - 1720",
      "1400 - 1720",
      "1600 - 1720",
      "1300 - 1450",
      "1500 - 1650",
      "0800 - 0950",
      "0900 - 1150",
      "0900 - 1020",
      "1500 - 1550",
      "1400 - 1630",
      "0800 - 0920",
      "1530 - 1650",
      "0800 - 0850",
      "1700 - 1820",
      "1530 - 1620",
      "2000 - 2050",
      "0800 - 1150",
      "1200 - 1550",
      "1230 - 1620",
      "0830 - 0920",
      "1500 - 1750",
      "1300 - 1650",
      "1500 - 1620",
      "1700 - 1850",
      "0900 - 1050",
      "1100 - 1250",
      "1200 - 1320",
      "1600 - 1750",
      "1600 - 1650",
      "1000 - 1120",
      "1130 - 1250",
      "1030 - 1150",
      "1300 - 1420",
      "1600 - 1730",
      "1230 - 1320",
      "1330 - 1520",
      "1530 - 1710",
      "1630 - 1750",
      "1430 - 1550",
      "1730 - 1850",
      "1730 - 1920",
      "1000 - 1150",
      "1530 - 1820",
      "1700 - 1750",
      "1100 - 1215",
      "0800 - 0959",
      "1530 - 1730",
      "1500 - 1700",
      "1700 - 1900",
      "1730 - 1930",
      "0600 - 0730",
      "1700 - 1950",
      "1200 - 1450",
      "1500 - 1730",
      "0930 - 1020",
      "1730 - 2030",
      "1300 - 1550",
      "1730 - 1900",
      "1830 - 1950",
      "1100 - 1350",
      "1800 - 2050",
      "1300 - 1520",
      "1300 - 1750",
      "1030 - 1120",
      "1430 - 1520",
      "1630 - 1720",
      "1130 - 1220",
      "0930 - 1220",
      "0800 - 1050",
      "1200 - 1420",
      "0930 - 1120",
      "1800 - 1950",
      "1600 - 1840",
      "1400 - 1640",
      "1700 - 1940",
      "0930 - 1210",
      "0900 - 1140",
      "1300 - 1540",
      "1330 - 1450",
      "1530 - 1800",
      "1400 - 1700",
      "1930 - 2050",
      "1830 - 2020",
      "0900 - 1220",
      "1300 - 1620",
      "1100 - 1450",
      "1500 - 1850",
      "1600 - 1850",
      "1400 - 1515",
      "1530 - 1645",
      "1700 - 1815",
      "1830 - 1945",
      "1230 - 1345",
      "1600 - 1740",
      "1200 - 1350",
      "1900 - 2050",
      "1530 - 1720",
      "1800 - 2100",
      "0900 - 1120",
      "1800 - 1920",
      "1200 - 1650",
      "1630 - 1920",
      "1100 - 1330",
      "0930 - 1200",
      "1000 - 2000",
      "1300 - 1430",
      "1830 - 2130",
      "1830 - 2100",
      "1600 - 1700",
      "1700 - 1800",
      "1000 - 1250",
      "1630 - 1745",
      "1630 - 1730",
      "1730 - 1845",
      "1300 - 1415",
      "1300 - 1600",
      "1000 - 1220",
      "1430 - 1820",
      "0900 - 1030",
      "1035 - 1150",
      "1430 - 1630",
      "1450 - 1735",
      "1400 - 1620",
      "1530 - 1750",
      "1145 - 1305",
      "0830 - 0950",
      "1100 - 1230",
      "1600 - 1800",
      "1800 - 2000",
      "1900 - 1930",
      "0730 - 1530",
      "1530 - 1550",
      "1000 - 1700",
      "1630 - 1800",
      "1100 - 1320",
      "1230 - 1430",
      "1200 - 1430",
      "1000 - 1200",
      "1700 - 2000",
      "1730 - 2020",
      "0900 - 1200",
      "1730 - 2130",
      "0900 - 1600",
      "1900 - 2200",
      "1900 - 1950",
      "1500 - 1615",
      "0800 - 1220"
    ],
    "dateRanges": [],
    "scheduleTypes": [
      "Lecture-Discussion",
      "Discussion/ Recitation",
      "Lecture",
      "Online",
      "Independent Study",
      "Laboratory-Discussion",
      "Laboratory",
      "Online Lecture",
      "Online Discussion",
      "Conference",
      "Online Lecture Discussion",
      "Seminar",
      "Study Abroad",
      "Internship",
      "Research",
      "Travel",
      "Studio",
      "Online Lab",
      "Practice",
      "Quiz"
    ],
    "campuses": [],
    "attributes": [],
    "restrictions": [],
    "gradeBases": [],
    "locations": [
      {
        "lat": 40.1047599,
        "long": -88.2319514
      },
      {
        "lat": 40.105732,
        "long": -88.2281018
      },
      {
        "lat": 40.10755766472843,
        "long": -88.22995430218522
      },
      {
        "lat": 40.10628,
        "long": -88.22621
      },
      {
        "lat": 40.1065684,
        "long": -88.2281746
      },
      {
        "lat": 40.1072225,
        "long": -88.2262016
      },
      {
        "lat": 40.10944320239664,
        "long": -88.22602522743233
      },
      {
        "lat": null,
        "long": null
      },
      {
        "lat": 40.107534,
        "long": -88.2281548
      },
      {
        "lat": 40.103620555545135,
        "long": -88.22982720445013
      },
      {
        "lat": 40.106778040727896,
        "long": -88.2194617156191
      },
      {
        "lat": 40.1020773,
        "long": -88.2296394
      },
      {
        "lat": 40.102726858556835,
        "long": -88.23259991223857
      },
      {
        "lat": 40.11246109008789,
        "long": -88.22831726074219
      },
      {
        "lat": 40.1035833,
        "long": -88.228405
      },
      {
        "lat": 40.10127390836906,
        "long": -88.2226073524728
      },
      {
        "lat": 40.1035872,
        "long": -88.2306061
      },
      {
        "lat": 40.0995003,
        "long": -88.223104
      },
      {
        "lat": 40.101862,
        "long": -88.231737
      },
      {
        "lat": 40.1034533,
        "long": -88.2327596
      },
      {
        "lat": 40.103627234541904,
        "long": -88.22601765311099
      },
      {
        "lat": 40.103587,
        "long": -88.230606
      },
      {
        "lat": 40.104794,
        "long": -88.224264
      },
      {
        "lat": 40.107811,
        "long": -88.2260761
      },
      {
        "lat": 40.10783362157985,
        "long": -88.22476189569741
      },
      {
        "lat": 40.1033599,
        "long": -88.2292111
      },
      {
        "lat": 40.108419421661715,
        "long": -88.2261156301609
      },
      {
        "lat": 40.1083446,
        "long": -88.2282555
      },
      {
        "lat": 40.11380515934119,
        "long": -88.22490788390387
      },
      {
        "lat": 40.110811306674734,
        "long": -88.2248467072371
      },
      {
        "lat": 40.11171215875622,
        "long": -88.22530849701589
      },
      {
        "lat": 40.1109722,
        "long": -88.2282631
      },
      {
        "lat": 40.1131317,
        "long": -88.2264552
      },
      {
        "lat": 40.1108856,
        "long": -88.2269806
      },
      {
        "lat": 40.1110937,
        "long": -88.2232348
      },
      {
        "lat": 40.1149296,
        "long": -88.2280589
      },
      {
        "lat": 40.111691,
        "long": -88.2242511
      },
      {
        "lat": 40.10623714823253,
        "long": -88.2232659093846
      },
      {
        "lat": 40.1149521,
        "long": -88.2267561
      },
      {
        "lat": 40.1028373,
        "long": -88.2251326
      },
      {
        "lat": 40.092875494224195,
        "long": -88.22082220247309
      },
      {
        "lat": 40.1022093629303,
        "long": -88.22800864058527
      },
      {
        "lat": 40.105587640130146,
        "long": -88.22025111416733
      },
      {
        "lat": 40.10593795776367,
        "long": -88.2270736694336
      },
      {
        "lat": 40.108570819242026,
        "long": -88.22518453938676
      },
      {
        "lat": 40.11397164321797,
        "long": -88.2265192685827
      },
      {
        "lat": 40.11085653938169,
        "long": -88.22609810215927
      },
      {
        "lat": 40.10802885201532,
        "long": -88.22239700364068
      },
      {
        "lat": 40.11180304465921,
        "long": -88.22613003543475
      }
    ],
    "finalDates": [],
    "finalTimes": []
  }
}